cython_coverage.py
cython_coverage-0.0.0.dist-info/LICENSE.txt
cython_coverage-0.0.0.dist-info/METADATA
cython_coverage-0.0.0.dist-info/WHEEL
cython_coverage-0.0.0.dist-info/top_level.txt
cython_coverage-0.0.0.dist-info/RECORD
